README
setup.py
phpbb/__init__.py
phpbb/constants.py
phpbb/functions.py
phpbb/auth/__init__.py
phpbb/auth/auth_db.py
phpbb/auth/backends.py
phpbb/auth/sql.py
phpbb/utf/__init__.py
phpbb/utf/data.py
phpbb/utf/utf_tools.py
phpbb_python.egg-info/PKG-INFO
phpbb_python.egg-info/SOURCES.txt
phpbb_python.egg-info/dependency_links.txt
phpbb_python.egg-info/top_level.txt