Metadata-Version: 1.0
Name: phpbb-python
Version: 0.0.1
Summary: phpBB authentication in Python
Home-page: https://github.com/japsu/phpbb-python
Author: Santtu Pajukanta
Author-email: santtu@pajukanta.fi
License: UNKNOWN
Platform: UNKNOWN
